{
  "project_info": {
    "project_number": "307065531115",
    "project_id": "food-delivery-eff48",
    "storage_bucket": "food-delivery-eff48.firebasestorage.app"
  },
  "client": [
    {
      "client_info": {
        "mobilesdk_app_id": "1:307065531115:android:d97e9400879a3327f32cae",
        "android_client_info": {
          "package_name": "com.example.food_delivery"
        }
      },
      "oauth_client": [],
      "api_key": [
        {
          "current_key": "AIzaSyC2fRPQ23gKq6Dbaa3_V12ibTLhVI2yJFA"
        }
      ],
      "services": {
        "appinvite_service": {
          "other_platform_oauth_client": []
        }
      }
    }
  ],
  "configuration_version": "1"
}